ebzl/__init__.py
ebzl/ebzl.py
ebzl/lib/__init__.py
ebzl/lib/config.py
ebzl/lib/eb.py
ebzl/lib/ec2.py
ebzl/lib/ecs.py
ebzl/lib/format.py
ebzl/lib/parameters.py
ebzl/lib/s3.py
ebzl/modules/__init__.py
ebzl/modules/bundle.py
ebzl/modules/create.py
ebzl/modules/delete.py
ebzl/modules/deploy.py
ebzl/modules/ecs.py
ebzl/modules/env.py
ebzl/modules/help.py
ebzl/modules/instances.py
ebzl/modules/list.py
ebzl/modules/version.py
ebzl-0.9.12.dist-info/DESCRIPTION.rst
ebzl-0.9.12.dist-info/entry_points.txt
ebzl-0.9.12.dist-info/METADATA
ebzl-0.9.12.dist-info/metadata.json
ebzl-0.9.12.dist-info/RECORD
ebzl-0.9.12.dist-info/top_level.txt
ebzl-0.9.12.dist-info/WHEEL
