Metadata-Version: 2.0
Name: ebzl
Version: 0.9.12
Summary: AWS ElasticBeanstalk management helper
Home-page: http://github.com/bearops/ebzl
Author: Wojciech Gaca
Author-email: gaca@dubizzle.com
License: MIT
Keywords: aws amazon web services elastic beanstalk eb application environment
Platform: UNKNOWN
Classifier: Development Status :: 4 - Beta
Classifier: Environment :: Console
Classifier: Intended Audience :: Developers
Classifier: License :: OSI Approved :: MIT License
Classifier: Programming Language :: Python :: 2.7
Classifier: Programming Language :: Python :: 3.0
Requires-Dist: boto (==2.38.0)
Requires-Dist: boto3 (==1.2.2)
